swdl/__init__.py
swdl/camera.py
swdl/club.py
swdl/config.py
swdl/labels.py
swdl/match_data.py
swdl/matches.py
swdl/swrest.py
swdl/team.py
swdl/tools.py
swdl-1.11.10.data/scripts/swdl-login
swdl-1.11.10.data/scripts/swdl-match-info
swdl-1.11.10.dist-info/LICENSE
swdl-1.11.10.dist-info/METADATA
swdl-1.11.10.dist-info/WHEEL
swdl-1.11.10.dist-info/top_level.txt
swdl-1.11.10.dist-info/RECORD
