Metadata-Version: 2.2
Name: swdl
Version: 1.11.10
Summary: Soccerwatch Data Library
Author-email: Christian Bodenstein <bodenstein@soccerwatch.tv>
Project-URL: Homepage, https://bitbucket.org/soccerwatch/swdl/
Requires-Python: >=3.8
License-File: LICENSE
Requires-Dist: future
Requires-Dist: google-cloud-storage
Requires-Dist: h5py
Requires-Dist: m3u8
Requires-Dist: mock
Requires-Dist: numpy
Requires-Dist: pandas
Requires-Dist: pydoc-markdown
Requires-Dist: requests
Requires-Dist: simplejson
Requires-Dist: tables
Requires-Dist: pytest
Requires-Dist: requests-mock
Requires-Dist: aiohttp
Provides-Extra: dev
Requires-Dist: pre-commit; extra == "dev"
Requires-Dist: pytest; extra == "dev"
